ExamplePack/__init__.py
whirldata/__init__.py
ExamplePack-0.1.3.dist-info/LICENSE
ExamplePack-0.1.3.dist-info/METADATA
ExamplePack-0.1.3.dist-info/WHEEL
ExamplePack-0.1.3.dist-info/top_level.txt
ExamplePack-0.1.3.dist-info/RECORD
